ctypes_screenshots/LICENSE
ctypes_screenshots/README.MD
ctypes_screenshots/__init__.py
ctypes_screenshots/requirements.txt
ctypes_screenshots/thirdparty.json
ctypes_screenshots-0.12.dist-info/LICENSE.rst
ctypes_screenshots-0.12.dist-info/METADATA
ctypes_screenshots-0.12.dist-info/WHEEL
ctypes_screenshots-0.12.dist-info/top_level.txt
ctypes_screenshots-0.12.dist-info/RECORD
