Metadata-Version: 2.1
Name: ctypes-screenshots
Version: 0.12
Summary: Takes screenshots without pywin32 dependency (whole screen/single window)
Home-page: https://github.com/hansalemaos/ctypes_screenshots
Author: Johannes Fischer
Author-email: <aulasparticularesdealemaosp@gmail.com>
License: MIT
Keywords: screenshots,ctypes
Classifier: Development Status :: 4 - Beta
Classifier: Programming Language :: Python :: 3 :: Only
Classifier: Programming Language :: Python :: 3.9
Classifier: Topic :: Scientific/Engineering :: Visualization
Classifier: Topic :: Software Development :: Libraries :: Python Modules
Classifier: Topic :: Text Editors :: Text Processing
Classifier: Topic :: Text Processing :: General
Classifier: Topic :: Text Processing :: Indexing
Classifier: Topic :: Text Processing :: Filters
Classifier: Topic :: Utilities
License-File: LICENSE.rst
Requires-Dist: mss
Requires-Dist: numpy
